cfile_properties_pkg/__init__.py
cfile_properties_pkg/cfile_properties.py
createf_example_pkg5-0.0.0.5.dist-info/LICENSE
createf_example_pkg5-0.0.0.5.dist-info/METADATA
createf_example_pkg5-0.0.0.5.dist-info/WHEEL
createf_example_pkg5-0.0.0.5.dist-info/top_level.txt
createf_example_pkg5-0.0.0.5.dist-info/RECORD
