Metadata-Version: 2.1
Name: createf-example-pkg5
Version: 0.0.0.5
Summary: A file create package
Home-page: https://github.com/pypa/sampleproject
Author: Nessa Kenny
Author-email: author@example.com
License: UNKNOWN
Platform: UNKNOWN
Classifier: Programming Language :: Python :: 3
Classifier: License :: OSI Approved :: MIT License
Classifier: Operating System :: OS Independent
Requires-Python: >=3.6
